option_util/__init__.py
option_util/expirations.py
option_util/futurescontract.py
option_util-0.3.4.dist-info/METADATA
option_util-0.3.4.dist-info/WHEEL
option_util-0.3.4.dist-info/RECORD
