Metadata-Version: 2.4
Name: option-util
Version: 0.3.4
Project-URL: Repository, https://github.com/dmckim1977/option-util
Project-URL: documentation, https://option-util.readthedocs.io/en/latest/#
Author-email: David Mckim <davidmckim@gmail.com>
Requires-Python: ~=3.10
Requires-Dist: pandas<3,>=2.2.3
Requires-Dist: python-dateutil<3,>=2.9.0.post0
